outlier/outlier.py
spyoutlier2-1.0.3.dist-info/LICENSE
spyoutlier2-1.0.3.dist-info/LICENSE.py
spyoutlier2-1.0.3.dist-info/METADATA
spyoutlier2-1.0.3.dist-info/WHEEL
spyoutlier2-1.0.3.dist-info/entry_points.txt
spyoutlier2-1.0.3.dist-info/top_level.txt
spyoutlier2-1.0.3.dist-info/RECORD
